[
	{"tf": "ETS2 motif2", "value": 0.047},
	{"tf": "MZF1 motif1", "value": 0.048},
	{"tf": "FEV motif2", "value": 0.055},
	{"tf": "ERG motif1", "value": 0.038},
	{"tf": "NR0B1 motif1", "value": 0.033},
	{"tf": "NFIC motif1", "value": 0.037},
	{"tf": "SRF motif1", "value": 0.034},
	{"tf": "TFAP2C motif3", "value": 0.032},
	{"tf": "HIVEP2 motif1", "value": 0.034},
	{"tf": "TCF23 motif1", "value": 0.036},
	{"tf": "EPAS1 motif1", "value": 0.041},
	{"tf": "NHLH2 motif1", "value": 0.033},
	{"tf": "ASCL2 motif1", "value": 0.034},
	{"tf": "NFKB1 motif3", "value": 0.041},
	{"tf": "ETS1 motif5", "value": 0.04},
	{"tf": "STAT3 motif1", "value": 0.042},
	{"tf": "NFKB2 motif1", "value": 0.034},
	{"tf": "ETV5 motif2", "value": 0.047},
	{"tf": "NHLH1 motif2", "value": 0.034},
	{"tf": "ETS2 motif1", "value": 0.045},
	{"tf": "BCL6 motif1", "value": 0.033},
	{"tf": "STAT5B motif1", "value": 0.035},
	{"tf": "TCF3 motif1", "value": 0.037},
	{"tf": "EGR2 motif2", "value": 0.034},
	{"tf": "SPI1 motif1", "value": 0.043},
	{"tf": "ZNF281 motif1", "value": 0.034},
	{"tf": "PTF1A motif1", "value": 0.042},
	{"tf": "STAT1 motif1", "value": 0.033},
	{"tf": "MZF1 motif2", "value": 0.041},
	{"tf": "TFAP4 motif2", "value": 0.039},
	{"tf": "RELB motif1", "value": 0.057},
	{"tf": "STAT1 motif4", "value": 0.035},
	{"tf": "NFKB1 motif1", "value": 0.039},
	{"tf": "NR3C1 motif1", "value": 0.036},
	{"tf": "ASCL1 motif1", "value": 0.032},
	{"tf": "NR2F6 motif3", "value": 0.033},
	{"tf": "ETS1 motif3", "value": 0.039},
	{"tf": "NHLH1 motif3", "value": 0.04},
	{"tf": "STAT4 motif1", "value": 0.038},
	{"tf": "ZBTB7B motif2", "value": 0.036},
	{"tf": "RELA motif1", "value": 0.056},
	{"tf": "NFKB1 motif2", "value": 0.039},
	{"tf": "PPARG motif3", "value": 0.034},
	{"tf": "LYL1 motif1", "value": 0.043},
	{"tf": "REL motif1", "value": 0.037},
	{"tf": "WT1 motif1", "value": 0.035},
	{"tf": "MAFK motif1", "value": 0.033},
	{"tf": "PATZ1 motif2", "value": 0.035},
	{"tf": "ZBTB7A motif2", "value": 0.034},
	{"tf": "STAT1 motif3", "value": 0.034}
]